[
   {
        "pk": 1,
        "model": "auxilioemergencial.tipoauxilio",
        "fields": {
			"titulo":"Serviço de Internet"
        }
   },
   {
        "pk": 2,
        "model": "auxilioemergencial.tipoauxilio",
        "fields": {
			"titulo":"Aquisição de Dispositivo Eletrônico"
        }
   },
   {
        "pk": 3,
        "model": "auxilioemergencial.tipoauxilio",
        "fields": {
			"titulo":"Material Didático Pedagógico"
        }
   },
   {
        "pk": 4,
        "model": "auxilioemergencial.tipoauxilio",
        "fields": {
			"titulo":"Projeto Alunos Conectados"
        }
   }
]
