[
{
    "model": "comum.funcaocodigo",
    "pk": 1,
    "fields": {
        "nome": "CD-01"
    }
},
{
    "model": "comum.funcaocodigo",
    "pk": 2,
    "fields": {
        "nome": "CD-02"
    }
},
{
    "model": "comum.funcaocodigo",
    "pk": 3,
    "fields": {
        "nome": "CD-03"
    }
},
{
    "model": "comum.funcaocodigo",
    "pk": 4,
    "fields": {
        "nome": "CD-04"
    }
},
{
    "model": "comum.funcaocodigo",
    "pk": 5,
    "fields": {
        "nome": "FG-01"
    }
},
{
    "model": "comum.funcaocodigo",
    "pk": 6,
    "fields": {
        "nome": "FG-02"
    }
},
{
    "model": "comum.funcaocodigo",
    "pk": 7,
    "fields": {
        "nome": "FG-03"
    }
},
{
    "model": "comum.funcaocodigo",
    "pk": 8,
    "fields": {
        "nome": "FG-04"
    }
},
{
    "model": "comum.funcaocodigo",
    "pk": 9,
    "fields": {
        "nome": "FG-05"
    }
},
{
    "model": "comum.funcaocodigo",
    "pk": 10,
    "fields": {
        "nome": "FG-06"
    }
},
{
    "model": "comum.funcaocodigo",
    "pk": 11,
    "fields": {
        "nome": "FG-07"
    }
},
{
    "model": "comum.funcaocodigo",
    "pk": 12,
    "fields": {
        "nome": "FG-08"
    }
},
{
    "model": "comum.funcaocodigo",
    "pk": 13,
    "fields": {
        "nome": "FG-09"
    }
},
{
    "model": "comum.funcaocodigo",
    "pk": 14,
    "fields": {
        "nome": "FUC-01"
    }
}
]


